rias/__main__.py
rias/compimg.py
rias/compvideo.py
rias/helper.py
rias/imgloader.py
rias-0.0.20.dist-info/LICENSE
rias-0.0.20.dist-info/METADATA
rias-0.0.20.dist-info/WHEEL
rias-0.0.20.dist-info/entry_points.txt
rias-0.0.20.dist-info/top_level.txt
rias-0.0.20.dist-info/RECORD
