Metadata-Version: 2.1
Name: rias
Version: 0.0.20
Summary: Rias CLI by Niffecs
Home-page: https://github.com/Niffecs/rias
Author: Niffecs
Author-email: niffecs@gmail.com
License: MIT
Classifier: Programming Language :: Python :: 3
Classifier: License :: OSI Approved :: MIT License
Classifier: Operating System :: OS Independent
Requires-Python: >=3.10
License-File: LICENSE
Requires-Dist: requests
Requires-Dist: six
Requires-Dist: chess
Requires-Dist: bs4
Requires-Dist: Pillow
